{
	"editor": {
		"current_page_number": 0,
		"page_view": 0,
		"text_size_id": 3
	},
	"pages": {
		"dropdown_dialog_arguments": [
			"amber-emotion",
			"eterna-emotion"
		],
		"dropdown_title_for_dialog_syntax": "character",
		"dropdown_titles": [
			"character",
			"amber-emotion",
			"eterna-emotion"
		],
		"dropdowns": {
			"amber-emotion": [
				"neutral",
				"happy",
				"scheming"
			],
			"character": [
				"amber",
				"eterna",
				"narrator"
			],
			"eterna-emotion": [
				"neutral",
				"annoyed"
			]
		},
		"empty_strings_for_l10n": false,
		"facts": {
			"player.against_rot": false,
			"player.asked_question": 0,
			"player.dig_free": false
		},
		"file_config": {
			"evaluator_paths": [
				"res://sample/inline_eval.gd"
			]
		},
		"head_defaults": [],
		"instruction_templates": {
			"black_fade": {
				"arg_types": [
					"float",
					"float",
					"float",
					"bool",
					"string",
					"string"
				],
				"args": [
					"fade_in",
					"hold_time",
					"fade_out",
					"hide_characters",
					"new_background",
					"new_bgm"
				]
			},
			"hide_cg": {
				"arg_types": [],
				"args": []
			},
			"play_sfx": {
				"arg_types": [
					"string"
				],
				"args": [
					"name"
				]
			},
			"set_background": {
				"arg_types": [
					"string",
					"float"
				],
				"args": [
					"name",
					"fade_time"
				]
			},
			"set_bgm": {
				"arg_types": [
					"string",
					"float"
				],
				"args": [
					"name",
					"fade_in"
				]
			},
			"set_text_style": {
				"arg_types": [
					"string"
				],
				"args": [
					"style"
				]
			},
			"show_cg": {
				"arg_types": [
					"string",
					"float",
					"bool"
				],
				"args": [
					"name",
					"fade_in_time",
					"continue_dialog_through_cg"
				]
			},
			"show_character": {
				"arg_types": [
					"string",
					"bool"
				],
				"args": [
					"character_name",
					"clear_others"
				]
			},
			"start_doom_timer": {
				"arg_types": [],
				"args": []
			}
		},
		"locales_to_export": [
			"af_ZA",
			"sq_AL",
			"ar_SA",
			"hy_AM",
			"az_AZ",
			"eu_ES",
			"be_BY",
			"bn_IN",
			"bs_BA",
			"bg_BG",
			"ca_ES",
			"zh_CN",
			"zh_TW",
			"hr_HR",
			"cs_CZ",
			"da_DK",
			"nl_NL",
			"en_US",
			"et_EE",
			"fo_FO",
			"fi_FI",
			"fr_FR",
			"gl_ES",
			"ka_GE",
			"de_DE",
			"el_GR",
			"gu_IN",
			"he_IL",
			"hi_IN",
			"hu_HU",
			"is_IS",
			"id_ID",
			"it_IT",
			"ja_JP",
			"kn_IN",
			"kk_KZ",
			"kok_IN",
			"ko_KR",
			"lv_LV",
			"lt_LT",
			"mk_MK",
			"ms_MY",
			"ml_IN",
			"mt_MT",
			"mr_IN",
			"mn_MN",
			"se_NO",
			"nb_NO",
			"nn_NO",
			"fa_IR",
			"pl_PL",
			"pt_BR",
			"pa_IN",
			"ro_RO",
			"ru_RU",
			"sr_BA",
			"sk_SK",
			"es_ES",
			"sw_KE",
			"sv_SE",
			"syr_SY",
			"ta_IN",
			"te_IN",
			"th_TH",
			"tn_ZA",
			"tr_TR",
			"uk_UA",
			"uz_UZ",
			"vi_VN",
			"cy_GB",
			"xh_ZA",
			"zu_ZA"
		],
		"page_data": {
			"0": {
				"facts": {
					"fact_data_by_name": {

					},
					"meta.visible": false
				},
				"lines": [
					{
						"address": "0.0",
						"conditionals": {
							"behavior": 0,
							"behavior_key": "Show",
							"facts": {
								"fact_data_by_name": {

								},
								"meta.visible": false
							},
							"meta.visible": false,
							"operand": 0,
							"operand_args": [],
							"operand_key": "AND"
						},
						"content": {
							"delay_after": 0,
							"delay_before": 0,
							"line_reader.args": [
								0,
								0.5,
								2,
								false,
								"workshop",
								"intro"
							],
							"meta.text": "black_fade(0.0, 0.5, 2.0, false, workshop, intro)",
							"meta.validation_status": "OK",
							"name": "black_fade"
						},
						"facts": {
							"fact_data_by_name": {

							},
							"meta.visible": false
						},
						"header": [],
						"line_type": 2,
						"meta.conditionals_visible": false,
						"meta.facts_visible": false,
						"meta.indent_level": 0,
						"meta.is_head_editable": false,
						"meta.line_index": 0,
						"meta.selector": {
							"selected": false
						}
					},
					{
						"address": "0.1",
						"conditionals": {
							"behavior": 0,
							"behavior_key": "Show",
							"facts": {
								"fact_data_by_name": {

								},
								"meta.visible": false
							},
							"meta.visible": false,
							"operand": 0,
							"operand_args": [],
							"operand_key": "AND"
						},
						"content": {
							"active_actors": [
								"amber",
								"eterna",
								"narrator"
							],
							"active_actors_title": "character",
							"content": "[]>amber{amber-emotion|happy,eterna-emotion|neutral}:Hi there! <ap>I'm Amber, and this is Eterna, and today we'll guide you through this delightful little demo of the DIISIS Plugin. <mp>Let's start with the basics. <lc>DIISIS is both a dialog editor, and a set of nodes in Godot to display the text that you have written. It's designed with narrative games in mind, so go wild with choices and a complicated world!\n[]>eterna:Just don't fall face-first into development hell..."
						},
						"facts": {
							"fact_data_by_name": {

							},
							"meta.visible": false
						},
						"header": [],
						"line_type": 0,
						"meta.conditionals_visible": false,
						"meta.facts_visible": false,
						"meta.indent_level": 0,
						"meta.is_head_editable": false,
						"meta.line_index": 1,
						"meta.selector": {
							"selected": false
						}
					},
					{
						"address": "0.2",
						"conditionals": {
							"behavior": 0,
							"behavior_key": "Show",
							"facts": {
								"fact_data_by_name": {

								},
								"meta.visible": false
							},
							"meta.visible": false,
							"operand": 0,
							"operand_args": [],
							"operand_key": "AND"
						},
						"content": {
							"auto_switch": false,
							"choices": [
								{
									"address": "0.2.0",
									"behavior_after_first_selection": 4,
									"choice_text.disabled": "",
									"choice_text.enabled": "I can't really code. Can I just make something?",
									"choice_text.enabled_as_default": true,
									"conditionals": {
										"behavior": 0,
										"behavior_key": "Show",
										"facts": {
											"fact_data_by_name": {

											},
											"meta.visible": false
										},
										"meta.visible": false,
										"operand": 0,
										"operand_args": [],
										"operand_key": "AND"
									},
									"do_jump_page": true,
									"facts": {
										"fact_data_by_name": {
											"player.asked_question": {
												"data_type": 1,
												"fact_name": "player.asked_question",
												"fact_value": 1,
												"int_comparator": 0,
												"int_operator": 1,
												"is_conditional": false
											}
										},
										"meta.visible": true
									},
									"loopback": true,
									"loopback_target_line": 3,
									"loopback_target_page": 0,
									"meta.jump_page_before_auto_switch": false,
									"meta.selector": {
										"selected": false
									},
									"target_line": 3,
									"target_page": 0
								},
								{
									"address": "0.2.1",
									"behavior_after_first_selection": 4,
									"choice_text.disabled": "",
									"choice_text.enabled": "How do I add complexity?",
									"choice_text.enabled_as_default": true,
									"conditionals": {
										"behavior": 0,
										"behavior_key": "Show",
										"facts": {
											"fact_data_by_name": {

											},
											"meta.visible": false
										},
										"meta.visible": false,
										"operand": 0,
										"operand_args": [],
										"operand_key": "AND"
									},
									"do_jump_page": true,
									"facts": {
										"fact_data_by_name": {
											"player.asked_question": {
												"data_type": 1,
												"fact_name": "player.asked_question",
												"fact_value": 1,
												"int_comparator": 0,
												"int_operator": 1,
												"is_conditional": false
											}
										},
										"meta.visible": true
									},
									"loopback": true,
									"loopback_target_line": 4,
									"loopback_target_page": 0,
									"meta.jump_page_before_auto_switch": false,
									"meta.selector": {
										"selected": false
									},
									"target_line": 4,
									"target_page": 0
								},
								{
									"address": "0.2.2",
									"behavior_after_first_selection": 4,
									"choice_text.disabled": "",
									"choice_text.enabled": "Does the HUD always look like this?",
									"choice_text.enabled_as_default": true,
									"conditionals": {
										"behavior": 0,
										"behavior_key": "Show",
										"facts": {
											"fact_data_by_name": {

											},
											"meta.visible": false
										},
										"meta.visible": false,
										"operand": 0,
										"operand_args": [],
										"operand_key": "AND"
									},
									"do_jump_page": true,
									"facts": {
										"fact_data_by_name": {
											"player.asked_question": {
												"data_type": 1,
												"fact_name": "player.asked_question",
												"fact_value": 1,
												"int_comparator": 0,
												"int_operator": 1,
												"is_conditional": false
											}
										},
										"meta.visible": true
									},
									"loopback": true,
									"loopback_target_line": 7,
									"loopback_target_page": 0,
									"meta.jump_page_before_auto_switch": false,
									"meta.selector": {
										"selected": false
									},
									"target_line": 5,
									"target_page": 0
								},
								{
									"address": "0.2.3",
									"behavior_after_first_selection": 4,
									"choice_text.disabled": "",
									"choice_text.enabled": "I want to do some crazy shit.",
									"choice_text.enabled_as_default": true,
									"conditionals": {
										"behavior": 0,
										"behavior_key": "Show",
										"facts": {
											"fact_data_by_name": {

											},
											"meta.visible": false
										},
										"meta.visible": false,
										"operand": 0,
										"operand_args": [],
										"operand_key": "AND"
									},
									"do_jump_page": true,
									"facts": {
										"fact_data_by_name": {
											"player.asked_question": {
												"data_type": 1,
												"fact_name": "player.asked_question",
												"fact_value": 1,
												"int_comparator": 0,
												"int_operator": 1,
												"is_conditional": false
											}
										},
										"meta.visible": true
									},
									"loopback": true,
									"loopback_target_line": 8,
									"loopback_target_page": 0,
									"meta.jump_page_before_auto_switch": false,
									"meta.selector": {
										"selected": false
									},
									"target_line": 8,
									"target_page": 0
								},
								{
									"address": "0.2.4",
									"behavior_after_first_selection": 0,
									"choice_text.disabled": "",
									"choice_text.enabled": "[continue] That's really cool.",
									"choice_text.enabled_as_default": true,
									"conditionals": {
										"behavior": 0,
										"behavior_key": "Show",
										"facts": {
											"fact_data_by_name": {
												"player.asked_question": {
													"data_type": 1,
													"fact_name": "player.asked_question",
													"fact_value": 0,
													"int_comparator": 0,
													"int_operator": 0,
													"is_conditional": true
												}
											},
											"meta.visible": true
										},
										"meta.visible": true,
										"operand": 0,
										"operand_args": [],
										"operand_key": "AND"
									},
									"do_jump_page": true,
									"facts": {
										"fact_data_by_name": {

										},
										"meta.visible": false
									},
									"loopback": false,
									"loopback_target_line": 0,
									"loopback_target_page": 0,
									"meta.jump_page_before_auto_switch": false,
									"meta.selector": {
										"selected": false
									},
									"target_line": 0,
									"target_page": 1
								},
								{
									"address": "0.2.5",
									"behavior_after_first_selection": 0,
									"choice_text.disabled": "",
									"choice_text.enabled": "[continue] Thank you for that info. What else?",
									"choice_text.enabled_as_default": true,
									"conditionals": {
										"behavior": 0,
										"behavior_key": "Show",
										"facts": {
											"fact_data_by_name": {
												"player.asked_question": {
													"data_type": 1,
													"fact_name": "player.asked_question",
													"fact_value": 0,
													"int_comparator": 4,
													"int_operator": 0,
													"is_conditional": true
												}
											},
											"meta.visible": true
										},
										"meta.visible": true,
										"operand": 0,
										"operand_args": [],
										"operand_key": "AND"
									},
									"do_jump_page": true,
									"facts": {
										"fact_data_by_name": {

										},
										"meta.visible": false
									},
									"loopback": false,
									"loopback_target_line": 0,
									"loopback_target_page": 0,
									"meta.jump_page_before_auto_switch": false,
									"meta.selector": {
										"selected": false
									},
									"target_line": 0,
									"target_page": 1
								}
							],
							"meta.do_jump_page": true
						},
						"facts": {
							"fact_data_by_name": {

							},
							"meta.visible": false
						},
						"header": [],
						"line_type": 1,
						"meta.conditionals_visible": false,
						"meta.facts_visible": false,
						"meta.indent_level": 0,
						"meta.is_head_editable": false,
						"meta.line_index": 2,
						"meta.selector": {
							"selected": false
						}
					},
					{
						"address": "0.3",
						"conditionals": {
							"behavior": 0,
							"behavior_key": "Show",
							"facts": {
								"fact_data_by_name": {

								},
								"meta.visible": false
							},
							"meta.visible": false,
							"operand": 0,
							"operand_args": [],
							"operand_key": "AND"
						},
						"content": {
							"active_actors": [
								"amber",
								"eterna",
								"narrator"
							],
							"active_actors_title": "character",
							"content": "[]>amber:Yesn't. DIISIS is very raw in many aspects, because you have to remember that at its core, it is literally just the node that spits out text to read and handles when to give the player dialog options. <mp>That being said, there are some common features of visual novels that basically everyone needs... <ap>This demo is basically a minimum template for just writing some text and have it appear on the screen.\n[]>eterna:In these files, you will find a simple save system and menu architecture. <mp>So as long as you spend the time learning how to use the DIISIS dialog editor, you should be fine with minimal coding experience."
						},
						"facts": {
							"fact_data_by_name": {

							},
							"meta.visible": false
						},
						"header": [],
						"line_type": 0,
						"meta.conditionals_visible": false,
						"meta.facts_visible": false,
						"meta.indent_level": 0,
						"meta.is_head_editable": false,
						"meta.line_index": 3,
						"meta.selector": {
							"selected": false
						}
					},
					{
						"address": "0.4",
						"conditionals": {
							"behavior": 0,
							"behavior_key": "Show",
							"facts": {
								"fact_data_by_name": {

								},
								"meta.visible": false
							},
							"meta.visible": false,
							"operand": 0,
							"operand_args": [],
							"operand_key": "AND"
						},
						"content": {
							"active_actors": [
								"amber",
								"eterna",
								"narrator"
							],
							"active_actors_title": "character",
							"content": "[]>amber:DIISIS comes with a [rainbow freq=2.0 sat=0.5 val=0.8]fact system[/rainbow]. <mp>At any point, you can declare a fact, which can be either a boolean (true or false) or an integer (any negative or positive whole number). <lc>Using this, you can hide / show lines of text and choices to make your game feel responsive. <mp>If you branch into different parts of the document (pages), you can even create entirely disjointed story paths! <lc>And secondly, you have choices themselves. They can have all kinds of anatomies, such as looping back to a start point (like this one)<mp>, or being a one-and-done deal (for more linear experiences).<lc> Furthermore, you can have options be picked automatically based on the state of some fact(s). All in all, it's really flexible!"
						},
						"facts": {
							"fact_data_by_name": {

							},
							"meta.visible": false
						},
						"header": [],
						"line_type": 0,
						"meta.conditionals_visible": false,
						"meta.facts_visible": false,
						"meta.indent_level": 0,
						"meta.is_head_editable": false,
						"meta.line_index": 4,
						"meta.selector": {
							"selected": false
						}
					},
					{
						"address": "0.5",
						"conditionals": {
							"behavior": 0,
							"behavior_key": "Show",
							"facts": {
								"fact_data_by_name": {

								},
								"meta.visible": false
							},
							"meta.visible": false,
							"operand": 0,
							"operand_args": [],
							"operand_key": "AND"
						},
						"content": {
							"delay_after": 0,
							"delay_before": 0,
							"line_reader.args": [
								"ToCharacter"
							],
							"meta.text": "set_text_style(ToCharacter)",
							"meta.validation_status": "OK",
							"name": "set_text_style"
						},
						"facts": {
							"fact_data_by_name": {

							},
							"meta.visible": false
						},
						"header": [],
						"line_type": 2,
						"meta.conditionals_visible": false,
						"meta.facts_visible": false,
						"meta.indent_level": 0,
						"meta.is_head_editable": false,
						"meta.line_index": 5,
						"meta.selector": {
							"selected": false
						}
					},
					{
						"address": "0.6",
						"conditionals": {
							"behavior": 0,
							"behavior_key": "Show",
							"facts": {
								"fact_data_by_name": {

								},
								"meta.visible": false
							},
							"meta.visible": false,
							"operand": 0,
							"operand_args": [],
							"operand_key": "AND"
						},
						"content": {
							"active_actors": [
								"amber",
								"eterna",
								"narrator"
							],
							"active_actors_title": "character",
							"content": "[]>eterna{eterna-emotion|neutral}:No. You can add any theme or layout anchors as you like.\n[]>amber:The HUD is your canvas.\n[]>eterna:As you can observe, this even allows for dynamic UI, if you want to put in the work...\n[]>amber:Hehe."
						},
						"facts": {
							"fact_data_by_name": {

							},
							"meta.visible": false
						},
						"header": [],
						"line_type": 0,
						"meta.conditionals_visible": false,
						"meta.facts_visible": false,
						"meta.indent_level": 0,
						"meta.is_head_editable": false,
						"meta.line_index": 6,
						"meta.selector": {
							"selected": false
						}
					},
					{
						"address": "0.7",
						"conditionals": {
							"behavior": 0,
							"behavior_key": "Show",
							"facts": {
								"fact_data_by_name": {

								},
								"meta.visible": false
							},
							"meta.visible": false,
							"operand": 0,
							"operand_args": [],
							"operand_key": "AND"
						},
						"content": {
							"delay_after": 0,
							"delay_before": 0,
							"line_reader.args": [
								"ToBottom"
							],
							"meta.text": "set_text_style(ToBottom)",
							"meta.validation_status": "OK",
							"name": "set_text_style"
						},
						"facts": {
							"fact_data_by_name": {

							},
							"meta.visible": false
						},
						"header": [],
						"line_type": 2,
						"meta.conditionals_visible": false,
						"meta.facts_visible": false,
						"meta.indent_level": 0,
						"meta.is_head_editable": false,
						"meta.line_index": 7,
						"meta.selector": {
							"selected": false
						}
					},
					{
						"address": "0.8",
						"conditionals": {
							"behavior": 0,
							"behavior_key": "Show",
							"facts": {
								"fact_data_by_name": {

								},
								"meta.visible": false
							},
							"meta.visible": false,
							"operand": 0,
							"operand_args": [],
							"operand_key": "AND"
						},
						"content": {
							"active_actors": [
								"amber",
								"eterna",
								"narrator"
							],
							"active_actors_title": "character",
							"content": "[]>amber:And you can do that. The entire plugin is functionally just two or three nodes. (That you need to care about at least.) With \"Instructions\", you can do function calls to the rest of your project. <lc>With some integration, you can easily execute arbitrary code. <mp>And with the call tags in dialog texts themselves, you can even call things mid-way through...<mp> Such as <call:screenshake>this screenshake!"
						},
						"facts": {
							"fact_data_by_name": {

							},
							"meta.visible": false
						},
						"header": [],
						"line_type": 0,
						"meta.conditionals_visible": false,
						"meta.facts_visible": false,
						"meta.indent_level": 0,
						"meta.is_head_editable": false,
						"meta.line_index": 8,
						"meta.selector": {
							"selected": false
						}
					}
				],
				"meta.scroll_vertical": 0,
				"meta.selected": false,
				"next": 1,
				"number": 0,
				"page_key": "intro",
				"terminate": false
			},
			"1": {
				"facts": {
					"fact_data_by_name": {

					},
					"meta.visible": false
				},
				"lines": [
					{
						"address": "1.0",
						"conditionals": {
							"behavior": 0,
							"behavior_key": "Show",
							"facts": {
								"fact_data_by_name": {

								},
								"meta.visible": false
							},
							"meta.visible": false,
							"operand": 0,
							"operand_args": [],
							"operand_key": "AND"
						},
						"content": {
							"active_actors": [
								"amber",
								"eterna",
								"narrator"
							],
							"active_actors_title": "character",
							"content": "[]>amber{amber-emotion|scheming}:There isn't much else to say right now, except..."
						},
						"facts": {
							"fact_data_by_name": {

							},
							"meta.visible": false
						},
						"header": [],
						"line_type": 0,
						"meta.conditionals_visible": false,
						"meta.facts_visible": false,
						"meta.indent_level": 0,
						"meta.is_head_editable": false,
						"meta.line_index": 0,
						"meta.selector": {
							"selected": false
						}
					},
					{
						"address": "1.1",
						"conditionals": {
							"behavior": 0,
							"behavior_key": "Show",
							"facts": {
								"fact_data_by_name": {

								},
								"meta.visible": false
							},
							"meta.visible": false,
							"operand": 0,
							"operand_args": [],
							"operand_key": "AND"
						},
						"content": {
							"delay_after": 0,
							"delay_before": 0,
							"line_reader.args": [
								"snap"
							],
							"meta.text": "play_sfx(snap)",
							"meta.validation_status": "OK",
							"name": "play_sfx"
						},
						"facts": {
							"fact_data_by_name": {

							},
							"meta.visible": false
						},
						"header": [],
						"line_type": 2,
						"meta.conditionals_visible": false,
						"meta.facts_visible": false,
						"meta.indent_level": 0,
						"meta.is_head_editable": false,
						"meta.line_index": 1,
						"meta.selector": {
							"selected": false
						}
					},
					{
						"address": "1.2",
						"conditionals": {
							"behavior": 0,
							"behavior_key": "Show",
							"facts": {
								"fact_data_by_name": {

								},
								"meta.visible": false
							},
							"meta.visible": false,
							"operand": 0,
							"operand_args": [],
							"operand_key": "AND"
						},
						"content": {
							"delay_after": 0,
							"delay_before": 0,
							"line_reader.args": [
								0,
								3,
								3,
								true,
								"scrapyard",
								"rainy"
							],
							"meta.text": "black_fade(0.0, 3.0, 3.0, true, scrapyard, rainy)",
							"meta.validation_status": "OK",
							"name": "black_fade"
						},
						"facts": {
							"fact_data_by_name": {

							},
							"meta.visible": false
						},
						"header": [],
						"line_type": 2,
						"meta.conditionals_visible": false,
						"meta.facts_visible": false,
						"meta.indent_level": 0,
						"meta.is_head_editable": false,
						"meta.line_index": 2,
						"meta.selector": {
							"selected": false
						}
					},
					{
						"address": "1.3",
						"conditionals": {
							"behavior": 0,
							"behavior_key": "Show",
							"facts": {
								"fact_data_by_name": {

								},
								"meta.visible": false
							},
							"meta.visible": false,
							"operand": 0,
							"operand_args": [],
							"operand_key": "AND"
						},
						"content": {
							"active_actors": [
								"amber",
								"eterna",
								"narrator"
							],
							"active_actors_title": "character",
							"content": "[]>narrator:Your face is planted down in the ground. The cold wetness of mud makes it difficult to breathe. The stench of mulch fills your nostrils."
						},
						"facts": {
							"fact_data_by_name": {

							},
							"meta.visible": false
						},
						"header": [],
						"line_type": 0,
						"meta.conditionals_visible": false,
						"meta.facts_visible": false,
						"meta.indent_level": 0,
						"meta.is_head_editable": false,
						"meta.line_index": 3,
						"meta.selector": {
							"selected": false
						}
					},
					{
						"address": "1.4",
						"conditionals": {
							"behavior": 0,
							"behavior_key": "Show",
							"facts": {
								"fact_data_by_name": {

								},
								"meta.visible": false
							},
							"meta.visible": false,
							"operand": 0,
							"operand_args": [],
							"operand_key": "AND"
						},
						"content": {
							"auto_switch": false,
							"choices": [
								{
									"address": "1.4.0",
									"behavior_after_first_selection": 0,
									"choice_text.disabled": "",
									"choice_text.enabled": "Dig free",
									"choice_text.enabled_as_default": true,
									"conditionals": {
										"behavior": 0,
										"behavior_key": "Show",
										"facts": {
											"fact_data_by_name": {

											},
											"meta.visible": false
										},
										"meta.visible": false,
										"operand": 0,
										"operand_args": [],
										"operand_key": "AND"
									},
									"do_jump_page": false,
									"facts": {
										"fact_data_by_name": {
											"player.dig_free": {
												"data_type": 0,
												"fact_name": "player.dig_free",
												"fact_value": true,
												"int_comparator": 0,
												"int_operator": 0,
												"is_conditional": false
											}
										},
										"meta.visible": true
									},
									"loopback": false,
									"loopback_target_line": 0,
									"loopback_target_page": 0,
									"meta.jump_page_before_auto_switch": false,
									"meta.selector": {
										"selected": false
									},
									"target_line": 0,
									"target_page": 1
								},
								{
									"address": "1.4.1",
									"behavior_after_first_selection": 0,
									"choice_text.disabled": "",
									"choice_text.enabled": "Give up",
									"choice_text.enabled_as_default": true,
									"conditionals": {
										"behavior": 0,
										"behavior_key": "Show",
										"facts": {
											"fact_data_by_name": {

											},
											"meta.visible": false
										},
										"meta.visible": false,
										"operand": 0,
										"operand_args": [],
										"operand_key": "AND"
									},
									"do_jump_page": false,
									"facts": {
										"fact_data_by_name": {

										},
										"meta.visible": false
									},
									"loopback": false,
									"loopback_target_line": 0,
									"loopback_target_page": 0,
									"meta.jump_page_before_auto_switch": false,
									"meta.selector": {
										"selected": false
									},
									"target_line": 0,
									"target_page": 1
								}
							],
							"meta.do_jump_page": true
						},
						"facts": {
							"fact_data_by_name": {

							},
							"meta.visible": false
						},
						"header": [],
						"line_type": 1,
						"meta.conditionals_visible": false,
						"meta.facts_visible": false,
						"meta.indent_level": 0,
						"meta.is_head_editable": false,
						"meta.line_index": 4,
						"meta.selector": {
							"selected": false
						}
					},
					{
						"address": "1.5",
						"conditionals": {
							"behavior": 0,
							"behavior_key": "Show",
							"facts": {
								"fact_data_by_name": {
									"player.dig_free": {
										"data_type": 0,
										"fact_name": "player.dig_free",
										"fact_value": true,
										"int_comparator": 0,
										"int_operator": 0,
										"is_conditional": true
									}
								},
								"meta.visible": true
							},
							"meta.visible": true,
							"operand": 0,
							"operand_args": [],
							"operand_key": "AND"
						},
						"content": {
							"active_actors": [
								"amber",
								"eterna",
								"narrator"
							],
							"active_actors_title": "character",
							"content": "[]>narrator:But you are merely down in the dirt. A few strenuous muscle movements, and you are upright again. \n[]>eterna{eterna-emotion|annoyed}:You helped yourself. <ap>Good."
						},
						"facts": {
							"fact_data_by_name": {

							},
							"meta.visible": false
						},
						"header": [],
						"line_type": 0,
						"meta.conditionals_visible": true,
						"meta.facts_visible": false,
						"meta.indent_level": 0,
						"meta.is_head_editable": false,
						"meta.line_index": 5,
						"meta.selector": {
							"selected": false
						}
					},
					{
						"address": "1.6",
						"conditionals": {
							"behavior": 0,
							"behavior_key": "Show",
							"facts": {
								"fact_data_by_name": {
									"player.dig_free": {
										"data_type": 0,
										"fact_name": "player.dig_free",
										"fact_value": false,
										"int_comparator": 0,
										"int_operator": 0,
										"is_conditional": true
									}
								},
								"meta.visible": true
							},
							"meta.visible": true,
							"operand": 0,
							"operand_args": [],
							"operand_key": "AND"
						},
						"content": {
							"active_actors": [
								"amber",
								"eterna",
								"narrator"
							],
							"active_actors_title": "character",
							"content": "[]>narrator:Within seconds, you feel the back of your nape grabbed and lifted upwards. <lc>The cold and metallic digits are dextrous and frighteningly fast, as Amber removes some of the dirt from your hair."
						},
						"facts": {
							"fact_data_by_name": {

							},
							"meta.visible": false
						},
						"header": [],
						"line_type": 0,
						"meta.conditionals_visible": true,
						"meta.facts_visible": false,
						"meta.indent_level": 0,
						"meta.is_head_editable": false,
						"meta.line_index": 6,
						"meta.selector": {
							"selected": false
						}
					},
					{
						"address": "1.7",
						"conditionals": {
							"behavior": 0,
							"behavior_key": "Show",
							"facts": {
								"fact_data_by_name": {

								},
								"meta.visible": false
							},
							"meta.visible": false,
							"operand": 0,
							"operand_args": [],
							"operand_key": "AND"
						},
						"content": {
							"active_actors": [
								"amber",
								"eterna",
								"narrator"
							],
							"active_actors_title": "character",
							"content": "[]>amber{eterna-emotion|neutral,amber-emotion|neutral}:As you can see, dear interloper, you can truly make your game [tornado radius=1.0 freq=3.0 connected=1]look any way you want[/tornado].\n[]>eterna:That right there is BBCode support, btw.\n[]>amber:This Plugin comes with an absolute cornucopia of features and customizability, so read the [url=https://github.com/SnekOfSpice/dialog-editor/wiki/]wiki on GitHub[/url] or just explore for yourself in the editor!\n[]>narrator:Gladly open an issue there or come say hi on [url=https://x.com/SnekOfSpice]Twitter[/url] with any bits of thought and feedback :3\n[]>amber{amber-emotion|happy}:These links are all also in the main menu! Isn't that handy!\n[]>eterna:So get back there and then out there and create."
						},
						"facts": {
							"fact_data_by_name": {

							},
							"meta.visible": false
						},
						"header": [],
						"line_type": 0,
						"meta.conditionals_visible": false,
						"meta.facts_visible": false,
						"meta.indent_level": 0,
						"meta.is_head_editable": false,
						"meta.line_index": 7,
						"meta.selector": {
							"selected": false
						}
					}
				],
				"meta.scroll_vertical": 0,
				"meta.selected": false,
				"next": 1,
				"number": 1,
				"page_key": "",
				"terminate": true
			}
		},
		"text_lead_time_other_actor": 0.6,
		"text_lead_time_same_actor": 0.05,
		"use_dialog_syntax": true
	}
}